tap_ruddr/__init__.py
tap_ruddr/client.py
tap_ruddr/pagination.py
tap_ruddr/schemas/clients.json
tap_ruddr/schemas/project-expenses.json
tap_ruddr/schemas/project-members.json
tap_ruddr/schemas/project-other-items.json
tap_ruddr/schemas/project-roles.json
tap_ruddr/schemas/project-tasks.json
tap_ruddr/schemas/projects.json
tap_ruddr/schemas/time-entries.json
tap_ruddr/streams.py
tap_ruddr/tap.py
tap_ruddr-0.0.1.dist-info/LICENSE
tap_ruddr-0.0.1.dist-info/METADATA
tap_ruddr-0.0.1.dist-info/WHEEL
tap_ruddr-0.0.1.dist-info/entry_points.txt
tap_ruddr-0.0.1.dist-info/RECORD
