Metadata-Version: 2.1
Name: tap-ruddr
Version: 0.0.1
Summary: `tap-ruddr` is a Singer tap for ruddr, built with the Meltano Singer SDK.
License: Apache-2.0
Keywords: ELT,ruddr
Author: Jeff Lewis
Requires-Python: >=3.7.1,<3.12
Classifier: License :: OSI Approved :: Apache Software License
Classifier: Programming Language :: Python :: 3
Classifier: Programming Language :: Python :: 3.8
Classifier: Programming Language :: Python :: 3.9
Classifier: Programming Language :: Python :: 3.10
Classifier: Programming Language :: Python :: 3.11
Provides-Extra: s3
Requires-Dist: fs-s3fs (>=1.1.1,<2.0.0) ; extra == "s3"
Requires-Dist: requests (>=2.31.0,<3.0.0)
Requires-Dist: singer-sdk (>=0.28.0,<0.29.0)
